odoo10_addon_account_payment_return_import-10.0.1.0.0.99.dev3-py2.7-nspkg.pth
odoo/addons/account_payment_return_import/README.rst
odoo/addons/account_payment_return_import/__init__.py
odoo/addons/account_payment_return_import/__manifest__.py
odoo/addons/account_payment_return_import/i18n/account_payment_return_import.pot
odoo/addons/account_payment_return_import/i18n/am.po
odoo/addons/account_payment_return_import/i18n/ar.po
odoo/addons/account_payment_return_import/i18n/bg.po
odoo/addons/account_payment_return_import/i18n/ca.po
odoo/addons/account_payment_return_import/i18n/cs.po
odoo/addons/account_payment_return_import/i18n/de.po
odoo/addons/account_payment_return_import/i18n/el_GR.po
odoo/addons/account_payment_return_import/i18n/es.po
odoo/addons/account_payment_return_import/i18n/es_CR.po
odoo/addons/account_payment_return_import/i18n/es_EC.po
odoo/addons/account_payment_return_import/i18n/es_ES.po
odoo/addons/account_payment_return_import/i18n/es_MX.po
odoo/addons/account_payment_return_import/i18n/es_VE.po
odoo/addons/account_payment_return_import/i18n/et.po
odoo/addons/account_payment_return_import/i18n/fi.po
odoo/addons/account_payment_return_import/i18n/fr.po
odoo/addons/account_payment_return_import/i18n/gl.po
odoo/addons/account_payment_return_import/i18n/hr.po
odoo/addons/account_payment_return_import/i18n/hr_HR.po
odoo/addons/account_payment_return_import/i18n/it.po
odoo/addons/account_payment_return_import/i18n/lt.po
odoo/addons/account_payment_return_import/i18n/nl.po
odoo/addons/account_payment_return_import/i18n/nl_BE.po
odoo/addons/account_payment_return_import/i18n/pl.po
odoo/addons/account_payment_return_import/i18n/pt.po
odoo/addons/account_payment_return_import/i18n/pt_BR.po
odoo/addons/account_payment_return_import/i18n/pt_PT.po
odoo/addons/account_payment_return_import/i18n/ro.po
odoo/addons/account_payment_return_import/i18n/ru.po
odoo/addons/account_payment_return_import/i18n/sl.po
odoo10_addon_account_payment_return_import-10.0.1.0.0.99.dev3.dist-info/METADATA
odoo10_addon_account_payment_return_import-10.0.1.0.0.99.dev3.dist-info/RECORD
odoo10_addon_account_payment_return_import-10.0.1.0.0.99.dev3.dist-info/WHEEL
odoo10_addon_account_payment_return_import-10.0.1.0.0.99.dev3.dist-info/namespace_packages.txt
odoo10_addon_account_payment_return_import-10.0.1.0.0.99.dev3.dist-info/top_level.txt
